Workbook

Sheet 封面
A1: 风险损失测算模板
A3: 可直接计算成本、逾期利息、预期损失，支持多情景对比分析
A5: 使用说明: 1. 在"参数输入"表的黄色区域填写三档情景(乐观/基准/悲观)参数 2. "损失测算结果"自动计算逾期利息、预期损失、处置总成本、回收率并判定风险等级 3. 核心公式: - 逾期利息 = 本金 × 逾期利率 × 逾期天数/360(银行惯例) - 预期损失(EL) = 违约风险敞口(EAD) × 违约概率(PD) × 违约损失率(LGD) - 处置总成本 = 净预期损失 + 催收/诉讼成本 + 间接成本 + 机会成本 + 逾期利息 4. "逾期利息计算器"用于单笔逐日计息，"情景对比分析"用于决策对比 5. 所有公式已预设，修改参数后自动重算；适用于逾期应收、合同违约、投资损失、供应链中断等场景

Sheet 参数输入
A1: 参数名称 | B1: 说明 | C1: 乐观情景 | D1: 基准情景 | E1: 悲观情景 | F1: 单位 | G1: 备注
A2: 风险敞口本金 | B2: 面临风险的本金/应收账款/投资金额 | C2: 1000000 | D2: 1000000 | E2: 1000000 | F2: 元 | G2: 按实际业务填写
A3: 违约概率(PD) | B3: 对方违约的可能性(0-100%) | C3: 0.05 | D3: 0.15 | E3: 0.35 | F3: % | G3: 按历史数据或信用评级估算
A4: 违约损失率(LGD) | B4: 违约后无法收回的比例(0-100%) | C4: 0.2 | D4: 0.4 | E4: 0.7 | F4: % | G4: 考虑抵押/担保/回收成本
A5: 逾期天数 | B5: 预计或已逾期的天数 | C5: 30 | D5: 90 | E5: 180 | F5: 天 | G5: 自到期日起算
A6: 逾期利率 | B6: 逾期利息年化利率 | C6: 0.12 | D6: 0.18 | E6: 0.24 | F6: % | G6: 合同约定或法定利率(LPR倍数)
A7: 催收/诉讼成本 | B7: 直接处置成本(律师费/诉讼费/催收费等) | C7: 5000 | D7: 20000 | E7: 50000 | F7: 元 | G7: 按处置方式估算
A8: 间接成本 | B8: 管理层时间/声誉损失/关系维护等 | C8: 10000 | D8: 30000 | E8: 80000 | F8: 元 | G8: 量化估计
A9: 机会成本率 | B9: 资金占用期间的机会成本年化率 | C9: 0.08 | D9: 0.1 | E9: 0.15 | F9: % | G9: 企业资金成本或投资回报率
A10: 保险赔付比例 | B10: 预计保险公司赔付比例(0=未投保) | C10: 0 | D10: 0.3 | E10: 0.6 | F10: % | G10: 以保单条款为准
A11: 担保覆盖比例 | B11: 担保方可覆盖比例(0=无担保) | C11: 0 | D11: 0.2 | E11: 0.5 | F11: % | G11: 以担保合同为准

Sheet 损失测算结果
A1: 测算项目 | B1: 计算公式 | C1: 乐观情景 | D1: 基准情景 | E1: 悲观情景 | F1: 单位 | G1: 说明
A2: 逾期利息 | B2: 本金 × 逾期利率 × 逾期天数/360 | C2: =参数输入!$C$2*参数输入!$C$6*参数输入!$C$5/360 | D2: =参数输入!$D$2*参数输入!$D$6*参数输入!$D$5/360 | E2: =参数输入!$E$2*参数输入!$E$6*参数输入!$E$5/360 | F2: 元 | G2: 资金占用成本
A3: 违约风险敞口(EAD) | B3: 本金 | C3: =参数输入!$C$2 | D3: =参数输入!$D$2 | E3: =参数输入!$E$2 | F3: 元 | G3: 面临损失的本金
A4: 预期损失(EL) | B4: EAD × PD × LGD | C4: =C3*参数输入!$C$3*参数输入!$C$4 | D4: =D3*参数输入!$D$3*参数输入!$D$4 | E4: =E3*参数输入!$E$3*参数输入!$E$4 | F4: 元 | G4: 信用风险核心指标
A5: 催收/诉讼成本 | B5: 直接处置费用 | C5: =参数输入!$C$7 | D5: =参数输入!$D$7 | E5: =参数输入!$E$7 | F5: 元 | G5: 直接成本
A6: 间接成本 | B6: 管理层时间/声誉/关系等 | C6: =参数输入!$C$8 | D6: =参数输入!$D$8 | E6: =参数输入!$E$8 | F6: 元 | G6: 间接成本
A7: 机会成本 | B7: 本金 × 机会成本率 × 逾期天数/360 | C7: =参数输入!$C$2*参数输入!$C$9*参数输入!$C$5/360 | D7: =参数输入!$D$2*参数输入!$D$9*参数输入!$D$5/360 | E7: =参数输入!$E$2*参数输入!$E$9*参数输入!$E$5/360 | F7: 元 | G7: 资金占用机会成本
A8: 保险赔付 | B8: 预期损失 × 保险赔付比例 | C8: =C4*参数输入!$C$10 | D8: =D4*参数输入!$D$10 | E8: =E4*参数输入!$E$10 | F8: 元 | G8: 风险转移回收
A9: 担保回收 | B9: 预期损失 × 担保覆盖比例 | C9: =C4*参数输入!$C$11 | D9: =D4*参数输入!$D$11 | E9: =E4*参数输入!$E$11 | F9: 元 | G9: 担保方代偿
A10: 净预期损失 | B10: 预期损失 - 保险赔付 - 担保回收 | C10: =C4-C8-C9 | D10: =D4-D8-D9 | E10: =E4-E8-E9 | F10: 元 | G10: 扣除风险转移后的净损失
A11: 处置总成本 | B11: 净预期损失+催收+间接+机会成本+逾期利息 | C11: =C10+C5+C6+C7+C2 | D11: =D10+D5+D6+D7+D2 | E11: =E10+E5+E6+E7+E2 | F11: 元 | G11: 总处置成本
A12: 损失率 | B12: 处置总成本 / 本金 | C12: =C11/C3 | D12: =D11/D3 | E12: =E11/E3 | F12: % | G12: 损失占本金比例
A13: 回收金额 | B13: 本金 - 处置总成本 | C13: =C3-C11 | D13: =D3-D11 | E13: =E3-E11 | F13: 元 | G13: 预计可回收金额
A14: 回收率 | B14: 回收金额 / 本金 | C14: =C13/C3 | D14: =D13/D3 | E14: =E13/E3 | F14: % | G14: 预计回收比例
A15: 风险等级判定(按损失率)
A16: 乐观情景 | B16: =IF(C12<0.05,"低风险",IF(C12<0.15,"中风险","高风险"))
A17: 基准情景 | B17: =IF(D12<0.05,"低风险",IF(D12<0.15,"中风险","高风险"))
A18: 悲观情景 | B18: =IF(E12<0.05,"低风险",IF(E12<0.15,"中风险","高风险"))
A19: 阈值说明: 损失率<5%低风险；5%-15%中风险；≥15%高风险

Sheet 逾期利息计算器
A1: 项目 | B1: 字段 | C1: 数值 | D1: 单位 | E1: 说明
A2: 本金 | B2: 逾期本金/应收账款金额 | C2: 1000000 | D2: 元 | E2: 填写实际金额
A3: 逾期利率 | B3: 年化利率(小数或%) | C3: 0.15 | D3: % | E3: 合同约定利率或LPR倍数
A4: 逾期天数 | B4: 从到期日到预计回收日 | C4: 90 | D4: 天 | E4: 实际逾期天数
A6: 计算结果
A7: 逾期利息 | B7: 本金 × 利率 × 天数/360 | C7: =C2*C3*C4/360 | D7: 元 | E7: 银行惯例360天计息
A8: 本息合计 | B8: 本金 + 逾期利息 | C8: =C2+C7 | D8: 元 | E8: 含本金总金额
A9: 日利息 | B9: 逾期利息 / 逾期天数 | C9: =C7/C4 | D9: 元/天 | E9: 每日资金占用成本
A10: 月利息 | B10: 日利息 × 30 | C10: =C9*30 | D10: 元/月 | E10: 每月资金占用成本

Sheet 情景对比分析
A1: 对比维度 | B1: 乐观情景 | C1: 基准情景 | D1: 悲观情景 | E1: 差异分析 | F1: 决策建议
A2: 处置总成本 | B2: =损失测算结果!C11 | C2: =损失测算结果!D11 | D2: =损失测算结果!E11 | E2: 悲观 vs 乐观差额 | F2: 悲观总成本>本金的20%时，考虑打折和解或债务重组
A3: 回收金额 | B3: =损失测算结果!C13 | C3: =损失测算结果!D13 | D3: =损失测算结果!E13 | E3: 悲观 vs 乐观差额 | F3: 回收金额<本金的50%时，优先保住核心客户关系
A4: 回收率 | B4: =损失测算结果!C14 | C4: =损失测算结果!D14 | D4: =损失测算结果!E14 | E4: 悲观 vs 乐观差额 | F4: 回收率<30%时，考虑债务重组或债转股
A5: 净预期损失 | B5: =损失测算结果!C10 | C5: =损失测算结果!D10 | D5: =损失测算结果!E10 | E5: 悲观 vs 乐观差额 | F5: 净损失>年利润10%时，启动专项止损程序
A6: 建议止损线 | B6: =参数输入!$C$2*0.15 | C6: =参数输入!$D$2*0.30 | D6: =参数输入!$E$2*0.50 | E6: 止损阈值设定 | F6: 达到止损线果断决策，避免延迟处置导致成本指数增长
A7: 处置策略建议 | B7: 正常催收(发函+电话跟进) | C7: 加强催收+法律手段(保全/诉讼) | D7: 评估放弃/重组/转让债权的期权 | E7: 拖延成本指数增长 | F7: 参考《黑天鹅》: 拖延是最大的成本，尽早处置优于观察 | G7: FALSE
